jaws/__init__.py
jaws/aaws2nc.py
jaws/analysis.py
jaws/clearsky.py
jaws/common.py
jaws/fsds_adjust.py
jaws/gcnet2nc.py
jaws/imau2nc.py
jaws/jaws.py
jaws/nsidc2nc.py
jaws/promice2nc.py
jaws/scar2nc.py
jaws/sunposition.py
jaws/tilt_angle.py
jaws/resources/cleardays.csv
jaws/resources/lst_para_rdn.txt
jaws/resources/stations.txt
jaws/resources/aaws/columns.txt
jaws/resources/aaws/ds.json
jaws/resources/aaws/encoding.json
jaws/resources/aaws/original_columns.json
jaws/resources/gcnet/columns.txt
jaws/resources/gcnet/ds.json
jaws/resources/gcnet/ds_derived.json
jaws/resources/gcnet/encoding.json
jaws/resources/gcnet/original_columns.json
jaws/resources/gcnet/quality_control.json
jaws/resources/imau/ant/columns.txt
jaws/resources/imau/ant/ds.json
jaws/resources/imau/ant/encoding.json
jaws/resources/imau/grl/columns.txt
jaws/resources/imau/grl/ds.json
jaws/resources/imau/grl/encoding.json
jaws/resources/nsidc/columns.txt
jaws/resources/nsidc/ds.json
jaws/resources/nsidc/encoding.json
jaws/resources/promice/aliases.txt
jaws/resources/promice/columns.txt
jaws/resources/promice/ds.json
jaws/resources/promice/encoding.json
jaws/resources/promice/original_columns.json
jaws/resources/scar/columns.txt
jaws/resources/scar/ds.json
jaws/resources/scar/encoding.json
jaws/resources/scar/original_columns.json
jaws-1.0.dist-info/METADATA
jaws-1.0.dist-info/RECORD
jaws-1.0.dist-info/WHEEL
jaws-1.0.dist-info/entry_points.txt
jaws-1.0.dist-info/top_level.txt
tests/__init__.py
tests/test.py
